processing/__init__.py
processing/cli.py
processing/constants.py
processing/interfaces.py
processing/main.py
processing/actions/__init__.py
processing/actions/autocluster.py
processing/actions/compute_requirements.py
processing/actions/digest.py
processing/actions/export_computation_umaps.py
processing/actions/export_dataframe.py
processing/actions/export_mdm.py
processing/actions/extract_and_aggregate.py
processing/actions/fix_audio_windows_10_7_2.py
processing/actions/purge_requirements.py
processing/actions/reduce.py
processing/actions/refresh_configuration.py
processing/actions/repack_storage.py
processing/actions/trace_relative_trajectories.py
processing/actions/trace_trajectories.py
processing/common/AggregatedLabelStorage.py
processing/common/AggregatedReduceable.py
processing/common/AggregatedStorage.py
processing/common/AutoclusteredStorage.py
processing/common/ComputationUmapStorage.py
processing/common/ContinuousTimeTrajectory.py
processing/common/FileLoader.py
processing/common/FileWalker.py
processing/common/Interval.py
processing/common/MeanDistancesMatrix.py
processing/common/MenuChoice.py
processing/common/RelativeTracedStorage.py
processing/common/Timeline.py
processing/common/TimelineWalker.py
processing/common/TracedStorage.py
processing/common/TrajectoryConfigError.py
processing/common/__init__.py
processing/config/Config.py
processing/config/ConfigParser.py
processing/config/ExcelSheet.py
processing/config/__init__.py
processing/config/autoclusters/AutoclusterConfig.py
processing/config/autoclusters/AutoclusterExcel.py
processing/config/autoclusters/AutoclusterStorage.py
processing/config/autoclusters/__init__.py
processing/config/bands/BandConfig.py
processing/config/bands/BandExcel.py
processing/config/bands/BandStorage.py
processing/config/bands/__init__.py
processing/config/binary/BinaryStorage.py
processing/config/binary/__init__.py
processing/config/digesters/DigesterConfig.py
processing/config/digesters/DigesterSheet.py
sound_scape_explorer_test-13.0.1.dist-info/METADATA
sound_scape_explorer_test-13.0.1.dist-info/WHEEL
sound_scape_explorer_test-13.0.1.dist-info/entry_points.txt
sound_scape_explorer_test-13.0.1.dist-info/top_level.txt
sound_scape_explorer_test-13.0.1.dist-info/RECORD
