Metadata-Version: 2.1
Name: sound-scape-explorer-test
Version: 13.0.1
Summary: SoundScapeExplorer
Author-email: Bamdad Sabbagh <hi@bamdad.fr>
Requires-Dist: wheel
Requires-Dist: numpy ==1.23.5
Requires-Dist: pandas ==1.5.3
Requires-Dist: h5py ==3.8.0
Requires-Dist: torch ==2.0.0
Requires-Dist: torchaudio ==2.0.1
Requires-Dist: umap ==0.1.1
Requires-Dist: umap-learn ==0.5.3
Requires-Dist: hdbscan ==0.8.33
Requires-Dist: scikit-learn ==1.2.2
Requires-Dist: pydub ==0.25.1
Requires-Dist: openpyxl ==3.1.2
Requires-Dist: mutagen ==1.46.0
Requires-Dist: rich ==13.5.2
Requires-Dist: inquirerpy ==0.3.4
